fvi/__init__.py
fvi/main.py
fvi-2.2.dist-info/entry_points.txt
fvi-2.2.dist-info/WHEEL
fvi-2.2.dist-info/METADATA
fvi-2.2.dist-info/RECORD
