Metadata-Version: 2.1
Name: fvi
Version: 2.2
Summary: Open those files that contain a string in Vim
Keywords: grep,vi,vim,gvim
Author: Ken Kundert
Author-email: fvi@nurdletech.com
Requires-Python: >=3.6
Classifier: Development Status :: 5 - Production/Stable
Classifier: Intended Audience :: Developers
Classifier: License :: OSI Approved :: GNU General Public License v3 or later (GPLv3+)
Classifier: Natural Language :: English
Classifier: Operating System :: POSIX :: Linux
Classifier: Programming Language :: Python :: 3
Classifier: Topic :: Utilities
Requires-Dist: appdirs
Requires-Dist: docopt
Requires-Dist: inform
Requires-Dist: nestedtext
Requires-Dist: shlib
Project-URL: changelog, https://github.com/KenKundert/fvi/blob/master/CHANGELOG.rst
Project-URL: documentation, https://github.com/KenKundert/fvi/blob/master/README.rst
Project-URL: homepage, https://github.com/kenkundert/fvi
Project-URL: repository, https://github.com/kenkundert/fvi
